botobackoff/__init__.py
botobackoff/botobackoff.py
botobackoff-0.0.2.dist-info/LICENSE.md
botobackoff-0.0.2.dist-info/METADATA
botobackoff-0.0.2.dist-info/WHEEL
botobackoff-0.0.2.dist-info/top_level.txt
botobackoff-0.0.2.dist-info/RECORD
