Metadata-Version: 2.1
Name: botobackoff
Version: 0.0.2
Summary: boto3 retry and backoff utility
Home-page: https://github.com/ericmaustin/botobackoff
Author: Eric Austin
Author-email: eric.m.austin@gmail.com
License: MIT
Requires-Python: >=3.7
License-File: LICENSE.md
Requires-Dist: boto3 (>=1.16.0)
Requires-Dist: botocore
